{
    "question": [
        {
            "title": "Ажылыктын бир ваажиби калып кетсе кантип толуктайт?",
            "answers": {
                "5 дирхам берип": false,
                "1 кой союп ": true,
                "3 күн орозо кармап": false,
                "1 кедей тойгузуп": false
            }
        },
        {
            "title": "Ислам динин эң биринчи кабыл алган аял киши?",
            "answers": {
                "Фатима р.а.": false,
                "Халима р.а.": false,
                "Айша р.а.": false,
                "Хадича р.а": true
            }
        },
        {
            "title": "Эң биринчи шейит болгон мусулман эркек?",
            "answers": {
                "Ясир р.а": true,
                "Абу Бакр": false,
                "Билал р.а.": false,
                "Абу Зар р.а.": false
            }
        },
        {
            "title": "Эң биринчи шейит болгон мусулман аял?",
            "answers": {
                "Амина": false,
                "Марьям": false,
                "Сумаййа": true,
                "Хадича": false
            }
        },
        {
            "title": "Пайгамбарыбыз с.а.в. Меккеликтерди Исламга чакыруу үчүн кайсы дөбөгө чыгып кыйкырган?",
            "answers": {
                "Хира": false,
                "Сафаа": true,
                "Марва": false,
                "Савр": false
            }
        },
        {
            "title": "Пайгамбарыбыз с.а.в.дын пайгамбарлык мөөрү денесинин кайсы жеринде болгон?",
            "answers": {
                "Колунда": false,
                "Эки далысынын ортосунда ": true,
                "Бутунда": false,
                "Эч кандай мөөр жок": false
            }
        },
        {
            "title": "Аллах тааланын канча ысымы бар?",
            "answers": {
                "99": true,
                "100": false,
                "1": false,
                "көп эле": false
            }
        },
        {
            "title": "Пайгамбарыбыз с.а.в. дын эң жакын досу ким болгон?",
            "answers": {
                "Билал": false,
                "Абу Талиб": false,
                "Rocketonia": false,
                "Абу Бакр ": true
            }
        },
        {
            "title": "- ... көздүн нуру.",
            "answers": {
                "Зикр": false,
                " Зекет": false,
                "Намаз": true,
                " Садака ": false
            }
        },
        {
            "title": "Куранда аты аталган аял?",
            "answers": {
                "Мариям ": true,
                "Хадича": false,
                "Барра": false,
                "Амина": false
            }
        },
        {
            "title": "Эң биринчи кайсы сүрөө тушкөн?",
            "answers": {
                "Фатиха": false,
                "Бакара сүрөөсүндөгү алгачкы 10 аят": false,
                "Йаасин": false,
                "Алак сүрөөсүнүн алгачкы 5 аяты ": true
            }
        },
        {
            "title": "Кыямат башталганда сурнай тарта турган периште?",
            "answers": {
                "Жабраил": false,
                "Исрафил": true,
                "Микаил": false,
                "Баары": false
            }
        },
        {
            "title": "Беш убак намаз кайсы түнү парз болгон?",
            "answers": {
                "Орозонун алгачкы түнүндө": false,
                "Кадыр түнү": false,
                "Мираж түнү ": true,
                "Айт майрам түнү": false
            }
        },
        {
            "title": "Мусулмандардын ыйык күнү?",
            "answers": {
                "Жума күнү ": true,
                "Кадыр күнү": false,
                "Дүйшөмбү күнү": false,
                "8-март күнү": false
            }
        },
        {
            "title": "Периштелер эмнеден жаратылган?",
            "answers": {
                "Оттон": false,
                "Нурдан": true,
                "Топурактан": false,
                "Кабыргадан": false
            }
        },
        {
            "title": "Периштелер эмнеден жаратылган?",
            "answers": {
                "Оттон": false,
                "Нурдан": true,
                "Топурактан": false,
                "Кабыргадан": false
            }
        },
        {
            "title": "Шайтандар эмнеден жаратылган?",
            "answers": {
                "Нурдан": false,
                "Топурактан": false,
                "Оттон": true,
                "Кабыргадан": false
            }
        },
        {
            "title": "Күн шооласы чачкан күндөрдүн эң жакшысы ....",
            "answers": {
                "Шаршемби": false,
                "Жума": true,
                "Ишемби": false,
                "Дүйшөмбү": false
            }
        },
        {
            "title": "Пайгамбарыбыз с.а.в. канча перзенттүү болгон?",
            "answers": {
                "7": true,
                "6": false,
                "4": false,
                "5": false
            }
        },
        {
            "title": "Бейиш ______ таманын астында?",
            "answers": {
                "Атанын": false,
                "Байкенин": false,
                "Эженин": false,
                "Эненин": true
            }
        },
        {
            "title": "Исламга кирүү үчүн эмне кылуу керек?",
            "answers": {
                "Орозот кармоо": false,
                "Шахадат келмесин айтуу ": true,
                "Бисмиллах айтуу": false,
                "Намаз окуу": false
            }
        },
        {
            "title": "Ажылыкка баруу кимдерге парз?",
            "answers": {
                "Оттон": false,
                "Нурдан": true,
                "Топурактан": false,
                "Кабыргадан": false
            }
        },
        {
            "title": "Периштелер эмнеден жаратылган?",
            "answers": {
                "Кулга": false,
                "Жетим-жесирге": false,
                "Мусулман болгон соо адамга ": true,
                "Соо адамга": false
            }
        },
        {
            "title": "Ислам аалымдары боюнча кыз баланын балагат жашы канча?",
            "answers": {
                "9": true,
                "7": false,
                "10": false,
                "12": false
            }
        },
        {
            "title": "Ислам аалымдары боюнча эркек баланын балагат жашы канча?",
            "answers": {
                "7": false,
                "12": true,
                "15": false,
                "9": false
            }
        },
        {
            "title": "Багымдат намазы жалпы канча рекет?",
            "answers": {
                "төрт рекет сүннөт, эки рекет фарз": false,
                "төрт рекет фарз, эки рекет сүннөт": false,
                "Эки рекет сүннөт, эки рекет фарз ": true,
                "туура жооп жок": false
            }
        },
        {
            "title": "Аср (дигер) намазы жалпы канча рекет?",
            "answers": {
                "төрт рекет сүннөт": false,
                "Төрт рекет фарз ": true,
                "Эки рекет фарз": false,
                "туура жооп жок": false
            }
        },
        {
            "title": "Бешим намазы жалпы канча рекет?",
            "answers": {
                "Төрт рекет сүннөт, төрт рекет фарз, эки рекет сүннөт ": true,
                "Төрт рекет сүннөт, эки рекет фарз, эки рекет фарз": false,
                "Төрт рекет фарз, эки рекет сүннөт": false,
                "баары туура": false
            }
        },
        {
            "title": "Куптан намазы жалпы канча рекет?",
            "answers": {
                "Төрт рекет фарз, эки рекет сүннөт, үч рекет витр намазы": false,
                "Төрт рекет фарз, эки рекет сүннөт, үч рекет витр намазы ": true,
                "Төрт рекет фарз, эки рекет сүннөт, эки рекет витр намазы": false,
                "баары туура": false
            }
        },
        {
            "title": "Шам намазы жалпы канча рекет?",
            "answers": {
                "Үч рекет сүннөт, эки рекет фарз": false,
                "туура жооп жок": false,
                "Төрт рекет фарз, эки рекет сүннөт ": true,
                "Үч рекет фарз, эки рекет сүннөт": false
            }
        },
        {
            "title": "Ибрахим а.с. канча уулу болгон жана ысымдары?",
            "answers": {
                "2 уул. Исмаил , Исхак ": true,
                "3 уул. Исмаил, Али, Умар": false,
                "1 уул. Исмаил": false,
                "4 уул. Кинана, Исхак, Зайд, Усман": false
            }
        },
        {
            "title": "Амина энебиз пайгамбарыбыз с.а.в.ды төрөгөн кезде жанында болгон аялдар?",
            "answers": {
                "Шифа, Фатима ": true,
                "Халима, Сумаййа": false,
                "Насиба, Айман": false,
                "Хадича, СалимаRocketonia": false
            }
        },
        {
            "title": "Кимде -ким уктап калып же унутуп калып намазын окубаса, эстегенде .... (хадис)",
            "answers": {
                "Зикр кылсын": false,
                "Садака берсин": false,
                "Орозо кармасын": false,
                "Дароо окусун ": true
            }
        },
        {
            "title": "Үйлөөнүгө шарты жоктор Пайгамбарыбыз с.а.в.дын айтуусу боюнча .......... зарыл.",
            "answers": {
                "Намаз окуусу": false,
                "Зекет берүүсү": false,
                "Орозо кармоосу ": true,
                "Отун алуусу": false
            }
        },
        {
            "title": "Гусулда канча парз бар?",
            "answers": {
                "3": true,
                "7": false,
                "9": false,
                "4": false
            }
        },
        {
            "title": "Бүткүл денени атайын эреже боюнча жууш эмне деп аталат?",
            "answers": {
                "Таяммум": false,
                "Даарат": false,
                "Аталбайт": false,
                "Гусул": true
            }
        },
        {
            "title": "Канча жаштан намаз үйрөөнү керек?",
            "answers": {
                "15": false,
                "7": true,
                "9": false,
                "12": false
            }
        },
        {
            "title": "Ыйык китептер кимдерге вахий кылынган?",
            "answers": {
                "Аалымдарга": false,
                "Пайгамбарыбыз а.с.в.га": false,
                "Пайгамбарларга": true,
                "Олуяларга": false
            }
        },
        {
            "title": "Акыркы пайгамбар ким болгон?",
            "answers": {
                "Иса пайгамбар": false,
                "Муса пайгамбар": false,
                "Нух пайгамбар": false,
                "Мухаммед пайгамбар ": true
            }
        },
        {
            "title": "Куранда аты көп аталган пайгамбар ким?",
            "answers": {
                "Муса пайгамбар ": true,
                "Пайгамбарыбыз с.а.в": false,
                "Даут пайгамбар": false,
                "Нух пайгамбар": false
            }
        },
        {
            "title": "Куранда айтылган жан алуучу периште?",
            "answers": {
                " Исрафил ": false,
                "Жабраил": false,
                "Азраил": true,
                "Периште жан албайт": false
            }
        },
        {
            "title": "Аллах Тааладан аян алып келуучу периште?",
            "answers": {
                "Исрафил": false,
                "Азраил": false,
                "Периште": false,
                "Жабраил": true
            }
        },
        {
            "title": "Пайгамбарыбыз с.а.в. га жакшы маанай каалоо?",
            "answers": {
                "Салават": true,
                " Такбир": false,
                "Мактоо": false,
                "Зикр": false
            }
        },
        {
            "title": "........сөзү бизге фарс тилинен кирген. Бизче 'жол башчы', 'элчи' дегенмаанилерди берет?",
            "answers": {
                "Олуя": false,
                "Пайгамбар": true,
                "Муфтий": false,
                "Аалым": false
            }
        },
        {
            "title": "Сүннөт канчага бөлүнөт жана  кандай болуп?",
            "answers": {
                "2ге. Мубах, Мустахаб.": false,
                "4кө. Муфсид, Макрух, Гайру муаккад, Мубах.": false,
                "3кө. Муаккад, Гайру муаккад, Заваид. ": true,
                "Эми билип алам": false
            }
        },
        {
            "title": "Жайында ыссыкта орозо кармоо ден соолукка таасир этеби?",
            "answers": {
                "Пайда, ашказан тазаланат ": true,
                "Зыян, оорукчан болосуң": false,
                "3 күнү эле пайда": false,
                "Жайында орозо кармалбайт": false
            }
        },
        {
            "title": "Пайгамбарыбыз с.а.в.дын шакегинде кандай жазуу болгон?",
            "answers": {
                "Мухаммад Расулуллох ": true,
                "Аллах": false,
                "Ахмад": false,
                "Жазуу жок": false
            }
        },
        {
            "title": "Ажылыкта шайтанга канча даана таш ыргытуу важиб?",
            "answers": {
                "3": false,
                "7": false,
                "70": true,
                "40": false
            }
        },
        {
            "title": "Ажылык бүткөндөн кийин каабаны таваф кылуунун өкүмү?",
            "answers": {
                "Суннөт": false,
                "Важиб": true,
                " Мустахаб": false,
                " Парз ": false
            }
        },
        {
            "title": "Жер бетинде эң биринчи курулган мечит?",
            "answers": {
                "Акса мечити": false,
                "Аль Харам мечити ": true,
                "Куба мечити ": false,
                "баары туура": false
            }
        },
        {
            "title": "Тозоктун эн түбундө кимдер болот?",
            "answers": {
                "Каапырлар": false,
                " Мушриктер": false,
                " Жалганчылар": false,
                "Мунафыктар": true
            }
        },
        {
            "title": "Ыйык Каабада жайгашкан Аль-Харам мечитинде окулган бир намаздын сообу канча намаздын сообуна барабар?",
            "answers": {
                "100 000 намаздын ": true,
                "100 намаздын": false,
                "1000 намаздын": false,
                "10 000 намаздын": false
            }
        },
        {
            "title": "Тозоктун так ортосунда жайгашкан дарак эмне деп аталат? Тозокко тушкондөр анын мөмөсүнөн жеп азапталышат.",
            "answers": {
                "Туба": false,
                "Сидра": false,
                "Эми билип алам": false,
                "Заккум": true
            }
        },
        {
            "title": "Ажатканага ______бут менен кирип _____ бут менен чыгат?",
            "answers": {
                "Оң , сол": false,
                "Айырмасы жок": false,
                "Сол, оң ": true,
                "Сол, сол": false
            }
        },
        {
            "title": "Бүт ааламга ырыскы берүүчү Аллахтын кайсы ысымы?",
            "answers": {
                " Раззак ": true,
                "Ар-Рахман": false,
                "Аль-Маалик": false,
                "Аль-Куддус": false
            }
        }
    ]
}